car_racer/__init__.py
car_racer/car.png
car_racer/car.py
car_racer/config.py
car_racer/main.py
car_racer/tictoc.py
car_racer/track.py
car_racer-0.3.0b0.dist-info/LICENSE
car_racer-0.3.0b0.dist-info/METADATA
car_racer-0.3.0b0.dist-info/WHEEL
car_racer-0.3.0b0.dist-info/entry_points.txt
car_racer-0.3.0b0.dist-info/top_level.txt
car_racer-0.3.0b0.dist-info/RECORD
